{
  "signoffs": {
    "S1": {
      "decision": "approved",
      "decided_by": "shingshen@pisteyo.com",
      "decided_at": "2026-05-30T04:45:01.310479+00:00",
      "all_pass": true,
      "criteria": [
        {
          "key": "dc94e82878ead1ef",
          "verdict": "pass"
        },
        {
          "key": "9c8c80b4ae610463",
          "verdict": "pass"
        },
        {
          "key": "73a289e31c3188fb",
          "verdict": "pass"
        }
      ]
    },
    "S2": {
      "decision": "approved",
      "decided_by": "shingshen@pisteyo.com",
      "decided_at": "2026-05-30T04:56:33.464086+00:00",
      "all_pass": true,
      "criteria": [
        {
          "key": "d25edbba2773664a",
          "verdict": "pass"
        },
        {
          "key": "13d74e6c7db958d4",
          "verdict": "pass"
        }
      ]
    }
  },
  "generated_at": "2026-05-30T04:56:33.751699+00:00"
}
